wifigaze/__init__.py
wifigaze/__main__.py
wifigaze/hopchannels.py
wifigaze/processframe.py
wifigaze/server.py
wifigaze/tshark.py
wifigaze/webserver.py
wifigaze/static/favicon.ico
wifigaze/static/index.html
wifigaze/static/css/app.163a33a0.css
wifigaze/static/css/app.7287c6f5.css
wifigaze/static/js/app.18fb0282.js
wifigaze/static/js/app.18fb0282.js.map
wifigaze/static/js/app.2e1fca57.js
wifigaze/static/js/app.2e1fca57.js.map
wifigaze/static/js/app.56a3959f.js
wifigaze/static/js/app.56a3959f.js.map
wifigaze/static/js/app.faa5fe2c.js
wifigaze/static/js/app.faa5fe2c.js.map
wifigaze/static/js/chunk-vendors.aeaa2e20.js
wifigaze/static/js/chunk-vendors.aeaa2e20.js.map
wifigaze/static/js/chunk-vendors.d9ef2456.js
wifigaze/static/js/chunk-vendors.d9ef2456.js.map
wifigaze/static/js/chunk-vendors.ea282071.js
wifigaze/static/js/chunk-vendors.ea282071.js.map
wifigaze-0.5.0.dist-info/METADATA
wifigaze-0.5.0.dist-info/WHEEL
wifigaze-0.5.0.dist-info/entry_points.txt
wifigaze-0.5.0.dist-info/top_level.txt
wifigaze-0.5.0.dist-info/RECORD
