Metadata-Version: 2.4
Name: wifigaze
Version: 0.5.0
Summary: Visualise the wifi devices around you communicating to each other in their own networks
Author-email: feedthedogs <feedthedogs@hotmail.com>
License: MIT
Project-URL: Homepage, https://github.com/feedthedogs/wifigaze
Keywords: wifi,visualization,network
Classifier: Programming Language :: Python :: 3
Classifier: License :: OSI Approved :: MIT License
Classifier: Operating System :: OS Independent
Requires-Dist: quart
Requires-Dist: docopt
Requires-Dist: loguru
Requires-Dist: pyshark
